[
  {
    "name": "test-computed.vue",
    "bindings": [
      {
        "source": "a",
        "target": "span_5_8_5_28",
        "isEventBinding": false
      },
      {
        "source": "b",
        "target": "span_5_31_5_52",
        "isEventBinding": false
      },
      {
        "source": "answer",
        "target": "input_6_14_6_57",
        "isEventBinding": false
      },
      {
        "source": "input_6_14_6_57",
        "target": "answer",
        "isEventBinding": false
      },
      {
        "source": "may_check",
        "target": "button_7_8_15_17",
        "isEventBinding": false
      },
      {
        "source": "button_7_8_15_17",
        "target": "check_answer",
        "isEventBinding": true
      },
      {
        "source": "right",
        "target": "button_16_8_23_17",
        "isEventBinding": false
      },
      {
        "source": "right",
        "target": "button_24_8_31_17",
        "isEventBinding": false
      },
      {
        "source": "button_32_8_38_17",
        "target": "new_problem",
        "isEventBinding": true
      },
      {
        "source": "count_right",
        "target": "span_53_12_53_43",
        "isEventBinding": false
      },
      {
        "source": "count_wrong",
        "target": "span_56_12_56_43",
        "isEventBinding": false
      },
      {
        "source": "accuracy",
        "target": "span_59_12_59_40",
        "isEventBinding": false
      }
    ],
    "tagsInfo": [
      {
        "id": "span_5_8_5_28",
        "name": "a",
        "loc": {
          "start": {
            "line": 5,
            "column": 8
          },
          "end": {
            "line": 5,
            "column": 28
          }
        }
      },
      {
        "id": "span_5_31_5_52",
        "name": "b",
        "loc": {
          "start": {
            "line": 5,
            "column": 31
          },
          "end": {
            "line": 5,
            "column": 52
          }
        }
      },
      {
        "id": "input_6_14_6_57",
        "name": "input",
        "loc": {
          "start": {
            "line": 6,
            "column": 14
          },
          "end": {
            "line": 6,
            "column": 57
          }
        }
      },
      {
        "id": "button_7_8_15_17",
        "name": "Check",
        "loc": {
          "start": {
            "line": 7,
            "column": 8
          },
          "end": {
            "line": 15,
            "column": 17
          }
        }
      },
      {
        "id": "button_16_8_23_17",
        "name": "Right",
        "loc": {
          "start": {
            "line": 16,
            "column": 8
          },
          "end": {
            "line": 23,
            "column": 17
          }
        }
      },
      {
        "id": "button_24_8_31_17",
        "name": "Wrong",
        "loc": {
          "start": {
            "line": 24,
            "column": 8
          },
          "end": {
            "line": 31,
            "column": 17
          }
        }
      },
      {
        "id": "button_32_8_38_17",
        "name": "New Problem",
        "loc": {
          "start": {
            "line": 32,
            "column": 8
          },
          "end": {
            "line": 38,
            "column": 17
          }
        }
      },
      {
        "id": "span_53_12_53_43",
        "name": "count_right",
        "loc": {
          "start": {
            "line": 53,
            "column": 12
          },
          "end": {
            "line": 53,
            "column": 43
          }
        }
      },
      {
        "id": "span_56_12_56_43",
        "name": "count_wrong",
        "loc": {
          "start": {
            "line": 56,
            "column": 12
          },
          "end": {
            "line": 56,
            "column": 43
          }
        }
      },
      {
        "id": "span_59_12_59_40",
        "name": "accuracy",
        "loc": {
          "start": {
            "line": 59,
            "column": 12
          },
          "end": {
            "line": 59,
            "column": 40
          }
        }
      }
    ],
    "variableNames": [
      "a",
      "b",
      "c",
      "answer",
      "right",
      "count_right",
      "count_wrong"
    ],
    "methodNames": [
      "add_problem",
      "check_answer",
      "may_check",
      "new_problem"
    ],
    "calledInInit": [
      "add_problem"
    ],
    "init": {
      "name": "init",
      "writes": [],
      "reads": [],
      "calls": [
        "add_problem"
      ]
    },
    "computed": [
      {
        "name": "accuracy",
        "writes": [],
        "reads": [
          "count_wrong",
          "count_right"
        ],
        "calls": []
      }
    ],
    "methods": [
      {
        "name": "add_problem",
        "writes": [
          "c",
          "a",
          "b",
          "answer",
          "right"
        ],
        "reads": [
          "c",
          "a"
        ],
        "calls": []
      },
      {
        "name": "check_answer",
        "writes": [
          "right",
          "count_right",
          "count_wrong"
        ],
        "reads": [
          "c",
          "answer",
          "right"
        ],
        "calls": []
      },
      {
        "name": "may_check",
        "writes": [],
        "reads": [
          "answer",
          "right"
        ],
        "calls": []
      },
      {
        "name": "new_problem",
        "writes": [],
        "reads": [],
        "calls": [
          "add_problem"
        ]
      }
    ],
    "boundVariables": [
      "a",
      "b",
      "answer",
      "right",
      "count_right",
      "count_wrong"
    ],
    "boundMethods": [
      "check_answer",
      "may_check",
      "new_problem"
    ],
    "boundComputedVariables": [
      "accuracy"
    ]
  }
]